LICENSE
README.md
setup.py
Fiume/__init__.py
Fiume/cli.py
Fiume/config.py
Fiume/master.py
Fiume/metainfo_decoder.py
Fiume/prova.py
Fiume/state_machine.py
Fiume/test.py
Fiume/test3.py
Fiume/utils.py
Fiume.egg-info/PKG-INFO
Fiume.egg-info/SOURCES.txt
Fiume.egg-info/dependency_links.txt
Fiume.egg-info/entry_points.txt
Fiume.egg-info/requires.txt
Fiume.egg-info/top_level.txt
tests/__init__.py
tests/test_basics.py
tests/test_master_control_unit.py