Metadata-Version: 2.1
Name: Fiume
Version: 0.0.1.0
Summary: A Bittorrent client for single-file torrents.
Home-page: https://github.com/mattyonweb/fiume
Author: Matteo Cavada
Author-email: cvd00@insicuri.net
License: GNU General Public License v3.0
Platform: UNKNOWN
Classifier: License :: OSI Approved :: GNU General Public License v3 (GPLv3)
Classifier: Topic :: Internet
Classifier: Development Status :: 2 - Pre-Alpha
Classifier: Programming Language :: Python :: 3.9
Requires-Python: >=3.9
